ditdml/__init__.py
ditdml/data_interfaces/__init__.py
ditdml/data_interfaces/data_interface.py
ditdml/data_interfaces/data_interface_detail.py
ditdml/data_interfaces/data_interface_detail_test.py
ditdml/data_interfaces/data_interface_test.py
ditdml/data_interfaces/ihsj_data_interface.py
ditdml/data_interfaces/ihsj_data_interface_test.py
ditdml/data_interfaces/ihsj_reader.py
ditdml/data_interfaces/ihsjc_data_interface.py
ditdml/data_interfaces/ihsjc_data_interface_test.py
ditdml/data_interfaces/things_data_interface.py
ditdml/data_interfaces/things_data_interface_test.py
ditdml/data_interfaces/things_reader.py
ditdml/data_interfaces/things_reader_test.py
ditdml/data_interfaces/yummly_data_interface.py
ditdml/data_interfaces/yummly_data_interface_test.py
ditdml/data_interfaces/yummly_reader.py
ditdml/tools/__init__.py
ditdml/tools/report_data_statistics.py
ditdml/tools/visualization_utils.py
ditdml/tools/visualize_neighbors.py
ditdml/tools/visualize_similarity_matrix.py
ditdml/tools/visualize_triplets.py
ditdml-0.0.9.dist-info/LICENSE
ditdml-0.0.9.dist-info/METADATA
ditdml-0.0.9.dist-info/WHEEL
ditdml-0.0.9.dist-info/top_level.txt
ditdml-0.0.9.dist-info/RECORD
